{"md5":"317c1f3e1105ad4f41ee48878e3342f0","status":200,"elapsed":0.273587352,"data":[{"id":55604246,"start_date":"2005-09-04T21:00:00.000Z","end_date":"2005-10-22T21:00:00.000Z","abbreviation":[{"langcode":"fi","text":"1"},{"langcode":"sv","text":"1"},{"langcode":"en","text":"1"}],"name":[{"langcode":"fi","text":"2005-2006, 1. periodi"},{"langcode":"sv","text":"2005-2006, 1. perioden"},{"langcode":"en","text":"2005-2006, 1. period"}]},{"id":55604334,"start_date":"2005-10-30T22:00:00.000Z","end_date":"2005-12-17T22:00:00.000Z","abbreviation":[{"langcode":"fi","text":"2"},{"langcode":"sv","text":"2"},{"langcode":"en","text":"2"}],"name":[{"langcode":"fi","text":"2005-2006, 2. periodi"},{"langcode":"sv","text":"2005-2006, 2. perioden"},{"langcode":"en","text":"2005-2006, 2. period"}]},{"id":55604351,"start_date":"2006-01-15T22:00:00.000Z","end_date":"2006-03-04T22:00:00.000Z","abbreviation":[{"langcode":"fi","text":"3"},{"langcode":"sv","text":"3"},{"langcode":"en","text":"3"}],"name":[{"langcode":"fi","text":"2005-2006, 3. periodi"},{"langcode":"sv","text":"2005-2006, 3. perioden"},{"langcode":"en","text":"2005-2006, 3. period"}]},{"id":55604511,"start_date":"2006-03-12T22:00:00.000Z","end_date":"2006-05-06T21:00:00.000Z","abbreviation":[{"langcode":"fi","text":"4"},{"langcode":"sv","text":"4"},{"langcode":"en","text":"4"}],"name":[{"langcode":"fi","text":"2005-2006, 4. periodi"},{"langcode":"sv","text":"2005-2006, 4. perioden"},{"langcode":"en","text":"2005-2006, 4. period"}]},{"id":55604569,"start_date":"2006-09-03T21:00:00.000Z","end_date":"2006-10-21T21:00:00.000Z","abbreviation":[{"langcode":"fi","text":"1"},{"langcode":"sv","text":"1"},{"langcode":"en","text":"1"}],"name":[{"langcode":"fi","text":"2006-2007, 1. periodi"},{"langcode":"sv","text":"2006-2007, 1. perioden"},{"langcode":"en","text":"2006-2007, 1. period"}]},{"id":55608099,"start_date":"2006-10-29T22:00:00.000Z","end_date":"2006-12-16T22:00:00.000Z","abbreviation":[{"langcode":"fi","text":"2"},{"langcode":"sv","text":"2"},{"langcode":"en","text":"2"}],"name":[{"langcode":"fi","text":"2006-2007, 2. periodi"},{"langcode":"sv","text":"2006-2007, 2. perioden"},{"langcode":"en","text":"2006-2007, 2. period"}]},{"id":55608217,"start_date":"2007-01-14T22:00:00.000Z","end_date":"2007-03-03T22:00:00.000Z","abbreviation":[{"langcode":"fi","text":"3"},{"langcode":"sv","text":"3"},{"langcode":"en","text":"3"}],"name":[{"langcode":"fi","text":"2006-2007, 3. periodi"},{"langcode":"sv","text":"2006-2007, 3. perioden"},{"langcode":"en","text":"2006-2007, 3. period"}]},{"id":55608250,"start_date":"2007-03-11T22:00:00.000Z","end_date":"2007-05-05T21:00:00.000Z","abbreviation":[{"langcode":"fi","text":"4"},{"langcode":"sv","text":"4"},{"langcode":"en","text":"4"}],"name":[{"langcode":"fi","text":"2006-2007, 4. periodi"},{"langcode":"sv","text":"2006-2007, 4. perioden"},{"langcode":"en","text":"2006-2007, 4. period"}]},{"id":55608308,"start_date":"2007-09-02T21:00:00.000Z","end_date":"2007-10-20T21:00:00.000Z","abbreviation":[{"langcode":"fi","text":"1"},{"langcode":"sv","text":"1"},{"langcode":"en","text":"1"}],"name":[{"langcode":"fi","text":"2007-2008, 1. periodi"},{"langcode":"sv","text":"2007-2008, 1. perioden"},{"langcode":"en","text":"2007-2008, 1. period"}]},{"id":55608374,"start_date":"2007-10-28T22:00:00.000Z","end_date":"2007-12-15T22:00:00.000Z","abbreviation":[{"langcode":"fi","text":"2"},{"langcode":"sv","text":"2"},{"langcode":"en","text":"2"}],"name":[{"langcode":"fi","text":"2007-2008, 2. periodi"},{"langcode":"sv","text":"2007-2008, 2. perioden"},{"langcode":"en","text":"2007-2008, 2. period"}]},{"id":55608455,"start_date":"2008-01-13T22:00:00.000Z","end_date":"2008-03-01T22:00:00.000Z","abbreviation":[{"langcode":"fi","text":"3"},{"langcode":"sv","text":"3"},{"langcode":"en","text":"3"}],"name":[{"langcode":"fi","text":"2007-2008, 3. periodi"},{"langcode":"sv","text":"2007-2008, 3. periodi"},{"langcode":"en","text":"2007-2008, 3. period"}]},{"id":55608613,"start_date":"2008-03-09T22:00:00.000Z","end_date":"2008-05-03T21:00:00.000Z","abbreviation":[{"langcode":"fi","text":"4"},{"langcode":"sv","text":"4"},{"langcode":"en","text":"4"}],"name":[{"langcode":"fi","text":"2007-2008, 4. periodi"},{"langcode":"sv","text":"2007-2008, 4. periodi"},{"langcode":"en","text":"2007-2008, 4. period"}]},{"id":55609764,"start_date":"2008-08-31T21:00:00.000Z","end_date":"2008-10-18T21:00:00.000Z","abbreviation":[{"langcode":"fi","text":"1"},{"langcode":"sv","text":"1"},{"langcode":"en","text":"1"}],"name":[{"langcode":"fi","text":"2008-2009, 1. periodi"},{"langcode":"sv","text":"2008-2009, 1. perioden"},{"langcode":"en","text":"2008-2009, 1. period"}]},{"id":55609891,"start_date":"2008-10-26T22:00:00.000Z","end_date":"2008-12-13T22:00:00.000Z","abbreviation":[{"langcode":"fi","text":"2"},{"langcode":"sv","text":"2"},{"langcode":"en","text":"2"}],"name":[{"langcode":"fi","text":"2008-2009, 2. periodi"},{"langcode":"sv","text":"2008-2009, 2. perioden"},{"langcode":"en","text":"2008-2009, 2. period"}]},{"id":55609998,"start_date":"2009-01-11T22:00:00.000Z","end_date":"2009-02-28T22:00:00.000Z","abbreviation":[{"langcode":"fi","text":"3"},{"langcode":"sv","text":"3"},{"langcode":"en","text":"3"}],"name":[{"langcode":"fi","text":"2008-2009, 3. periodi"},{"langcode":"sv","text":"2008-2009, 3. perioden"},{"langcode":"en","text":"2008-2009, 3. period"}]},{"id":55610020,"start_date":"2009-03-08T22:00:00.000Z","end_date":"2009-05-16T21:00:00.000Z","abbreviation":[{"langcode":"fi","text":"4"},{"langcode":"sv","text":"4"},{"langcode":"en","text":"4"}],"name":[{"langcode":"fi","text":"2008-2009, 4. periodi"},{"langcode":"sv","text":"2008-2009, 4. perioden"},{"langcode":"en","text":"2008-2009, 4. period"}]},{"id":55610078,"start_date":"2009-09-06T21:00:00.000Z","end_date":"2009-10-24T21:00:00.000Z","abbreviation":[{"langcode":"fi","text":"1"},{"langcode":"sv","text":"1"},{"langcode":"en","text":"1"}],"name":[{"langcode":"fi","text":"2009-2010, 1. periodi"},{"langcode":"sv","text":"2009-2010, 1. perioden"},{"langcode":"en","text":"2009-2010, 1. perioden"}]},{"id":55610824,"start_date":"2009-11-01T22:00:00.000Z","end_date":"2009-12-19T22:00:00.000Z","abbreviation":[{"langcode":"fi","text":"2"},{"langcode":"sv","text":"2"},{"langcode":"en","text":"2"}],"name":[{"langcode":"fi","text":"2009-2010, 2. periodi"},{"langcode":"sv","text":"2009-2010, 2. perioden"},{"langcode":"en","text":"2009-2010, 2. period"}]},{"id":55610870,"start_date":"2010-01-17T22:00:00.000Z","end_date":"2010-03-06T22:00:00.000Z","abbreviation":[{"langcode":"fi","text":"3"},{"langcode":"sv","text":"3"},{"langcode":"en","text":"3"}],"name":[{"langcode":"fi","text":"2009-2010, 3. period"},{"langcode":"sv","text":"2009-2010, 3. perioden"},{"langcode":"en","text":"2009-2010, 3. period"}]},{"id":55611481,"start_date":"2010-03-14T22:00:00.000Z","end_date":"2010-05-22T21:00:00.000Z","abbreviation":[{"langcode":"fi","text":"4"},{"langcode":"sv","text":"4"},{"langcode":"en","text":"4"}],"name":[{"langcode":"fi","text":"2009-2010, 4. periodi"},{"langcode":"sv","text":"2009-2010, 4. perioden"},{"langcode":"en","text":"2009-2010, 4. period"}]},{"id":55611683,"start_date":"2010-09-05T21:00:00.000Z","end_date":"2010-10-23T21:00:00.000Z","abbreviation":[{"langcode":"fi","text":"1"},{"langcode":"sv","text":"1"},{"langcode":"en","text":"1"}],"name":[{"langcode":"fi","text":"2010-2011, 1. periodi"},{"langcode":"sv","text":"2010-2011, 1. perioden"},{"langcode":"en","text":"2010-2011, 1. period"}]},{"id":55611713,"start_date":"2010-10-31T22:00:00.000Z","end_date":"2010-12-18T22:00:00.000Z","abbreviation":[{"langcode":"fi","text":"2"},{"langcode":"sv","text":"2"},{"langcode":"en","text":"2"}],"name":[{"langcode":"fi","text":"2010-2011, 2. periodi"},{"langcode":"sv","text":"2010-2011, 2. perioden"},{"langcode":"en","text":"2010-2011, 2. period"}]},{"id":55611743,"start_date":"2011-01-16T22:00:00.000Z","end_date":"2011-03-05T22:00:00.000Z","abbreviation":[{"langcode":"fi","text":"3"},{"langcode":"sv","text":"3"},{"langcode":"en","text":"3"}],"name":[{"langcode":"fi","text":"2010-2011, 3. periodi"},{"langcode":"sv","text":"2010-2011, 3. perioden"},{"langcode":"en","text":"2010-2011, 3. period"}]},{"id":55611765,"start_date":"2011-03-13T22:00:00.000Z","end_date":"2011-05-21T21:00:00.000Z","abbreviation":[{"langcode":"fi","text":"4"},{"langcode":"sv","text":"4"},{"langcode":"en","text":"4"}],"name":[{"langcode":"fi","text":"2010-2011, 4. periodi"},{"langcode":"sv","text":"2010-2011, 4. perioden"},{"langcode":"en","text":"2010-2011, 4. period"}]},{"id":55611812,"start_date":"2011-09-04T21:00:00.000Z","end_date":"2011-10-22T21:00:00.000Z","abbreviation":[{"langcode":"fi","text":"1"},{"langcode":"sv","text":"1"},{"langcode":"en","text":"1"}],"name":[{"langcode":"fi","text":"2011-2012, 1. periodi"},{"langcode":"sv","text":"2011-2012, 1. perioden"},{"langcode":"en","text":"2011-2012, 1. period"}]},{"id":55611845,"start_date":"2011-10-30T22:00:00.000Z","end_date":"2011-12-17T22:00:00.000Z","abbreviation":[{"langcode":"fi","text":"2"},{"langcode":"sv","text":"2"},{"langcode":"en","text":"2"}],"name":[{"langcode":"fi","text":"2011-2012, 2. periodi"},{"langcode":"sv","text":"2011-2012, 2. perioden"},{"langcode":"en","text":"2011-2012, 2. period"}]},{"id":55611894,"start_date":"2012-01-15T22:00:00.000Z","end_date":"2012-03-03T22:00:00.000Z","abbreviation":[{"langcode":"fi","text":"3"},{"langcode":"sv","text":"3"},{"langcode":"en","text":"3"}],"name":[{"langcode":"fi","text":"2011-2012, 3. periodi"},{"langcode":"sv","text":"2011-2012, 3. perioden"},{"langcode":"en","text":"2011-2012, 3. period"}]},{"id":55611916,"start_date":"2012-03-11T22:00:00.000Z","end_date":"2012-05-19T21:00:00.000Z","abbreviation":[{"langcode":"fi","text":"4"},{"langcode":"sv","text":"4"},{"langcode":"en","text":"4"}],"name":[{"langcode":"fi","text":"2011-2012, 4. periodi"},{"langcode":"sv","text":"2011-2012, 4. perioden"},{"langcode":"en","text":"2011-2012, 4. period"}]},{"id":55934087,"start_date":"2006-05-07T21:00:00.000Z","end_date":"2006-09-02T21:00:00.000Z","abbreviation":[{"langcode":"fi","text":"Kesä"},{"langcode":"sv","text":"Sommar"},{"langcode":"en","text":"Summer"}],"name":[{"langcode":"fi","text":"2005-2006, Kesä"},{"langcode":"sv","text":"2005-2006, Sommaren"},{"langcode":"en","text":"2005-2006, Summer"}]},{"id":55934088,"start_date":"2007-05-06T21:00:00.000Z","end_date":"2007-09-01T21:00:00.000Z","abbreviation":[{"langcode":"fi","text":"Kesä"},{"langcode":"sv","text":"Sommar"},{"langcode":"en","text":"Summer"}],"name":[{"langcode":"fi","text":"2006-2007, Kesä"},{"langcode":"sv","text":"2006-2007, Sommaren"},{"langcode":"en","text":"2006-2007, Summer"}]},{"id":55934089,"start_date":"2008-05-04T21:00:00.000Z","end_date":"2008-09-02T21:00:00.000Z","abbreviation":[{"langcode":"fi","text":"Kesä"},{"langcode":"sv","text":"Sommar"},{"langcode":"en","text":"Summer"}],"name":[{"langcode":"fi","text":"2007-2008, Kesä"},{"langcode":"sv","text":"2007-2008, Sommaren"},{"langcode":"en","text":"2007-2008, Summer"}]},{"id":55934095,"start_date":"2009-05-17T21:00:00.000Z","end_date":"2009-09-05T21:00:00.000Z","abbreviation":[{"langcode":"fi","text":"Kesä"},{"langcode":"sv","text":"Sommar"},{"langcode":"en","text":"Summer"}],"name":[{"langcode":"fi","text":"2008-2009, Kesä"},{"langcode":"sv","text":"2008-2009, Sommaren"},{"langcode":"en","text":"2008-2009, Summer"}]},{"id":55934100,"start_date":"2010-05-23T21:00:00.000Z","end_date":"2010-09-04T21:00:00.000Z","abbreviation":[{"langcode":"fi","text":"Kesä"},{"langcode":"sv","text":"Sommar"},{"langcode":"en","text":"Summer"}],"name":[{"langcode":"fi","text":"2009-2010, Kesä"},{"langcode":"sv","text":"2009-2010, Sommaren"},{"langcode":"en","text":"2009-2010, Summer"}]},{"id":55934101,"start_date":"2011-05-22T21:00:00.000Z","end_date":"2011-09-03T21:00:00.000Z","abbreviation":[{"langcode":"fi","text":"Kesä"},{"langcode":"sv","text":"Sommar"},{"langcode":"en","text":"Summer"}],"name":[{"langcode":"fi","text":"2010-2011, Kesä"},{"langcode":"sv","text":"2010-2011, Sommaren"},{"langcode":"en","text":"2010-2011, Summer"}]},{"id":55934102,"start_date":"2012-05-20T21:00:00.000Z","end_date":"2012-09-01T21:00:00.000Z","abbreviation":[{"langcode":"fi","text":"Kesä"},{"langcode":"sv","text":"Sommar"},{"langcode":"en","text":"Summer"}],"name":[{"langcode":"fi","text":"2011-2012, Kesä"},{"langcode":"sv","text":"2011-2012, Sommaren"},{"langcode":"en","text":"2011-2012, Summer"}]},{"id":68257462,"start_date":"2012-09-02T21:00:00.000Z","end_date":"2012-10-20T21:00:00.000Z","abbreviation":[{"langcode":"fi","text":"1"},{"langcode":"sv","text":"1"},{"langcode":"en","text":"1"}],"name":[{"langcode":"fi","text":"2012-2013, 1. periodi"},{"langcode":"sv","text":"2012-2013, 1. perioden"},{"langcode":"en","text":"2012-2013, 1. period"}]},{"id":68257463,"start_date":"2012-10-28T22:00:00.000Z","end_date":"2012-12-15T22:00:00.000Z","abbreviation":[{"langcode":"fi","text":"2"},{"langcode":"sv","text":"2"},{"langcode":"en","text":"2"}],"name":[{"langcode":"fi","text":"2012-2013, 2. periodi"},{"langcode":"sv","text":"2012-2013, 2. perioden"},{"langcode":"en","text":"2012-2013, 2. period"}]},{"id":68257464,"start_date":"2013-01-13T22:00:00.000Z","end_date":"2013-03-02T22:00:00.000Z","abbreviation":[{"langcode":"fi","text":"3"},{"langcode":"sv","text":"3"},{"langcode":"en","text":"3"}],"name":[{"langcode":"fi","text":"2012-2013, 3. periodi"},{"langcode":"sv","text":"2012-2013, 3. perioden"},{"langcode":"en","text":"2012-2013, 3. period"}]},{"id":68257465,"start_date":"2013-03-10T22:00:00.000Z","end_date":"2013-05-18T21:00:00.000Z","abbreviation":[{"langcode":"fi","text":"4"},{"langcode":"sv","text":"4"},{"langcode":"en","text":"4"}],"name":[{"langcode":"fi","text":"2012-2013, 4. periodi"},{"langcode":"sv","text":"2012-2013, 4. perioden"},{"langcode":"en","text":"2012-2013, 4. period"}]},{"id":68257466,"start_date":"2013-05-19T21:00:00.000Z","end_date":"2013-08-31T21:00:00.000Z","abbreviation":[{"langcode":"fi","text":"Kesä"},{"langcode":"sv","text":"Sommar"},{"langcode":"en","text":"Summer"}],"name":[{"langcode":"fi","text":"2012-2013, Kesä"},{"langcode":"sv","text":"2012-2013, Sommaren"},{"langcode":"en","text":"2012-2013, Summer"}]},{"id":68257592,"start_date":"2013-09-01T21:00:00.000Z","end_date":"2013-10-19T21:00:00.000Z","abbreviation":[{"langcode":"fi","text":"1"},{"langcode":"sv","text":"1"},{"langcode":"en","text":"1"}],"name":[{"langcode":"fi","text":"2013-2014, 1. periodi"},{"langcode":"sv","text":"2013-2014, 1. perioden"},{"langcode":"en","text":"2013-2014, 1. period"}]},{"id":68257594,"start_date":"2013-10-27T22:00:00.000Z","end_date":"2013-12-14T22:00:00.000Z","abbreviation":[{"langcode":"fi","text":"2"},{"langcode":"sv","text":"2"},{"langcode":"en","text":"2"}],"name":[{"langcode":"fi","text":"2013-2014, 2. periodi"},{"langcode":"sv","text":"2013-2014, 2. perioden"},{"langcode":"en","text":"2013-2014, 2. period"}]},{"id":68257595,"start_date":"2014-01-12T22:00:00.000Z","end_date":"2014-03-01T22:00:00.000Z","abbreviation":[{"langcode":"fi","text":"3"},{"langcode":"sv","text":"3"},{"langcode":"en","text":"3"}],"name":[{"langcode":"fi","text":"2013-2014, 3. periodi"},{"langcode":"sv","text":"2013-2014, 3. perioden"},{"langcode":"en","text":"2013-2014, 3. period"}]},{"id":68257596,"start_date":"2014-03-09T22:00:00.000Z","end_date":"2014-05-17T21:00:00.000Z","abbreviation":[{"langcode":"fi","text":"4"},{"langcode":"sv","text":"4"},{"langcode":"en","text":"4"}],"name":[{"langcode":"fi","text":"2013-2014, 4. periodi"},{"langcode":"sv","text":"2013-2014, 4. perioden"},{"langcode":"en","text":"2013-2014, 4. period"}]},{"id":68257598,"start_date":"2014-05-18T21:00:00.000Z","end_date":"2014-08-30T21:00:00.000Z","abbreviation":[{"langcode":"fi","text":"Kesä"},{"langcode":"sv","text":"Sommar"},{"langcode":"en","text":"Summer"}],"name":[{"langcode":"fi","text":"2013-2014, Kesä"},{"langcode":"sv","text":"2013-2014, Sommaren"},{"langcode":"en","text":"2013-2014, Summer"}]},{"id":68257719,"start_date":"2014-08-31T21:00:00.000Z","end_date":"2014-10-18T21:00:00.000Z","abbreviation":[{"langcode":"fi","text":"1"},{"langcode":"sv","text":"1"},{"langcode":"en","text":"1"}],"name":[{"langcode":"fi","text":"2014-2015, 1. periodi"},{"langcode":"sv","text":"2014-2015, 1. perioden"},{"langcode":"en","text":"2014-2015, 1. period"}]},{"id":68257720,"start_date":"2014-10-26T22:00:00.000Z","end_date":"2014-12-13T22:00:00.000Z","abbreviation":[{"langcode":"fi","text":"2"},{"langcode":"sv","text":"2"},{"langcode":"en","text":"2"}],"name":[{"langcode":"fi","text":"2014-2015, 2. periodi"},{"langcode":"sv","text":"2014-2015, 2. perioden"},{"langcode":"en","text":"2014-2015, 2. period"}]},{"id":68257722,"start_date":"2015-01-11T22:00:00.000Z","end_date":"2015-02-28T22:00:00.000Z","abbreviation":[{"langcode":"fi","text":"3"},{"langcode":"sv","text":"3"},{"langcode":"en","text":"3"}],"name":[{"langcode":"fi","text":"2014-2015, 3. periodi"},{"langcode":"sv","text":"2014-2015, 3. perioden"},{"langcode":"en","text":"2014-2015, 3. period"}]},{"id":68257723,"start_date":"2015-03-08T22:00:00.000Z","end_date":"2015-05-02T21:00:00.000Z","abbreviation":[{"langcode":"fi","text":"4"},{"langcode":"sv","text":"4"},{"langcode":"en","text":"4"}],"name":[{"langcode":"fi","text":"2014-2015, 4. periodi"},{"langcode":"sv","text":"2014-2015, 4. perioden"},{"langcode":"en","text":"2014-2015, 4. period"}]},{"id":68257725,"start_date":"2015-05-03T21:00:00.000Z","end_date":"2015-08-29T21:00:00.000Z","abbreviation":[{"langcode":"fi","text":"Kesä"},{"langcode":"sv","text":"Sommar"},{"langcode":"en","text":"Summer"}],"name":[{"langcode":"fi","text":"2014-2015, Kesä"},{"langcode":"sv","text":"2014-2015, Sommaren"},{"langcode":"en","text":"2014-2015, Summer"}]},{"id":68257771,"start_date":"2015-08-30T21:00:00.000Z","end_date":"2015-10-17T21:00:00.000Z","abbreviation":[{"langcode":"fi","text":"1"},{"langcode":"sv","text":"1"},{"langcode":"en","text":"1"}],"name":[{"langcode":"fi","text":"2015-2016, 1. periodi"},{"langcode":"sv","text":"2015-2016, 1. perioden"},{"langcode":"en","text":"2015-2016, 1. period"}]},{"id":68257772,"start_date":"2015-10-25T22:00:00.000Z","end_date":"2015-12-12T22:00:00.000Z","abbreviation":[{"langcode":"fi","text":"2"},{"langcode":"sv","text":"2"},{"langcode":"en","text":"2"}],"name":[{"langcode":"fi","text":"2015-2016, 2. periodi"},{"langcode":"sv","text":"2015-2016, 2. perioden"},{"langcode":"en","text":"2015-2016, 2. period"}]},{"id":68257773,"start_date":"2016-01-17T22:00:00.000Z","end_date":"2016-03-05T22:00:00.000Z","abbreviation":[{"langcode":"fi","text":"3"},{"langcode":"sv","text":"3"},{"langcode":"en","text":"3"}],"name":[{"langcode":"fi","text":"2015-2016, 3. periodi"},{"langcode":"sv","text":"2015-2016, 3. perioden"},{"langcode":"en","text":"2015-2016, 3. period"}]},{"id":68257776,"start_date":"2016-03-13T22:00:00.000Z","end_date":"2016-05-07T21:00:00.000Z","abbreviation":[{"langcode":"fi","text":"4"},{"langcode":"sv","text":"4"},{"langcode":"en","text":"4"}],"name":[{"langcode":"fi","text":"2015-2016, 4. periodi"},{"langcode":"sv","text":"2015-2016, 4. perioden"},{"langcode":"en","text":"2015-2016, 4. period"}]},{"id":68257777,"start_date":"2016-05-08T21:00:00.000Z","end_date":"2016-09-03T21:00:00.000Z","abbreviation":[{"langcode":"fi","text":"Kesä"},{"langcode":"sv","text":"Sommar"},{"langcode":"en","text":"Summer"}],"name":[{"langcode":"fi","text":"2015-2016, Kesä"},{"langcode":"sv","text":"2015-2016, Sommaren"},{"langcode":"en","text":"2015-2016, Summer"}]},{"id":68258108,"start_date":"2016-09-04T21:00:00.000Z","end_date":"2016-10-22T21:00:00.000Z","abbreviation":[{"langcode":"fi","text":"1"},{"langcode":"sv","text":"1"},{"langcode":"en","text":"1"}],"name":[{"langcode":"fi","text":"2016-2017, 1. periodi"},{"langcode":"sv","text":"2016-2017, 1. perioden"},{"langcode":"en","text":"2016-2017, 1. period"}]},{"id":68258109,"start_date":"2016-10-30T22:00:00.000Z","end_date":"2016-12-17T22:00:00.000Z","abbreviation":[{"langcode":"fi","text":"2"},{"langcode":"sv","text":"2"},{"langcode":"en","text":"2"}],"name":[{"langcode":"fi","text":"2016-2017, 2. periodi"},{"langcode":"sv","text":"2016-2017, 2. perioden"},{"langcode":"en","text":"2016-2017, 2. period"}]},{"id":68258110,"start_date":"2017-01-15T22:00:00.000Z","end_date":"2017-03-04T22:00:00.000Z","abbreviation":[{"langcode":"fi","text":"3"},{"langcode":"sv","text":"3"},{"langcode":"en","text":"3"}],"name":[{"langcode":"fi","text":"2016-2017, 3. periodi"},{"langcode":"sv","text":"2016-2017, 3. perioden"},{"langcode":"en","text":"2016-2017, 3. period"}]},{"id":68258111,"start_date":"2017-03-12T22:00:00.000Z","end_date":"2017-05-06T21:00:00.000Z","abbreviation":[{"langcode":"fi","text":"4"},{"langcode":"sv","text":"4"},{"langcode":"en","text":"4"}],"name":[{"langcode":"fi","text":"2016-2017, 4. periodi"},{"langcode":"sv","text":"2016-2017, 4. perioden"},{"langcode":"en","text":"2016-2017, 4. period"}]},{"id":68258112,"start_date":"2017-05-07T21:00:00.000Z","end_date":"2017-09-02T21:00:00.000Z","abbreviation":[{"langcode":"fi","text":"Kesä"},{"langcode":"sv","text":"Sommar"},{"langcode":"en","text":"Summer"}],"name":[{"langcode":"fi","text":"2016-2017, Kesä"},{"langcode":"sv","text":"2016-2017, Sommaren"},{"langcode":"en","text":"2016-2017, Summer"}]},{"id":68258160,"start_date":"2017-09-03T21:00:00.000Z","end_date":"2017-10-21T21:00:00.000Z","abbreviation":[{"langcode":"fi","text":"1"},{"langcode":"sv","text":"1"},{"langcode":"en","text":"1"}],"name":[{"langcode":"fi","text":"2017-2018, 1. periodi"},{"langcode":"sv","text":"2017-2018, 1. perioden"},{"langcode":"en","text":"2017-2018, 1. period"}]},{"id":68258161,"start_date":"2017-10-29T22:00:00.000Z","end_date":"2017-12-16T22:00:00.000Z","abbreviation":[{"langcode":"fi","text":"2"},{"langcode":"sv","text":"2"},{"langcode":"en","text":"2"}],"name":[{"langcode":"fi","text":"2017-2018, 2. periodi"},{"langcode":"sv","text":"2017-2018, 2. perioden"},{"langcode":"en","text":"2017-2018, 2. period"}]},{"id":68258162,"start_date":"2018-01-14T22:00:00.000Z","end_date":"2018-03-03T22:00:00.000Z","abbreviation":[{"langcode":"fi","text":"3"},{"langcode":"sv","text":"3"},{"langcode":"en","text":"3"}],"name":[{"langcode":"fi","text":"2017-2018, 3. periodi"},{"langcode":"sv","text":"2017-2018, 3. perioden"},{"langcode":"en","text":"2017-2018, 3. period"}]},{"id":68258163,"start_date":"2018-03-11T22:00:00.000Z","end_date":"2018-05-05T21:00:00.000Z","abbreviation":[{"langcode":"fi","text":"4"},{"langcode":"sv","text":"4"},{"langcode":"en","text":"4"}],"name":[{"langcode":"fi","text":"2017-2018, 4. periodi"},{"langcode":"sv","text":"2017-2018, 4. perioden"},{"langcode":"en","text":"2017-2018, 4. period"}]},{"id":68258164,"start_date":"2018-05-06T21:00:00.000Z","end_date":"2018-09-01T21:00:00.000Z","abbreviation":[{"langcode":"fi","text":"Kesä"},{"langcode":"sv","text":"Sommar"},{"langcode":"en","text":"Summer"}],"name":[{"langcode":"fi","text":"2017-2018, Kesä"},{"langcode":"sv","text":"2017-2018, Sommaren"},{"langcode":"en","text":"2017-2018, Summer"}]},{"id":68258199,"start_date":"2018-09-02T21:00:00.000Z","end_date":"2018-10-21T21:00:00.000Z","abbreviation":[{"langcode":"fi","text":"1"},{"langcode":"sv","text":"1"},{"langcode":"en","text":"1"}],"name":[{"langcode":"fi","text":"2018-2019, 1. periodi"},{"langcode":"sv","text":"2018-2019, 1. perioden"},{"langcode":"en","text":"2018-2019, 1. period"}]},{"id":68258201,"start_date":"2018-10-28T22:00:00.000Z","end_date":"2018-12-17T22:00:00.000Z","abbreviation":[{"langcode":"fi","text":"2"},{"langcode":"sv","text":"2"},{"langcode":"en","text":"2"}],"name":[{"langcode":"fi","text":"2018-2019, 2. periodi"},{"langcode":"sv","text":"2018-2019, 2. perioden"},{"langcode":"en","text":"2018-2019, 2. period"}]},{"id":68258202,"start_date":"2019-01-13T22:00:00.000Z","end_date":"2019-03-02T22:00:00.000Z","abbreviation":[{"langcode":"fi","text":"3"},{"langcode":"sv","text":"3"},{"langcode":"en","text":"3"}],"name":[{"langcode":"fi","text":"2018-2019, 3. periodi"},{"langcode":"sv","text":"2018-2019, 3. perioden"},{"langcode":"en","text":"2018-2019, 3. period"}]},{"id":68258204,"start_date":"2019-03-10T22:00:00.000Z","end_date":"2019-05-04T21:00:00.000Z","abbreviation":[{"langcode":"fi","text":"4"},{"langcode":"sv","text":"4"},{"langcode":"en","text":"4"}],"name":[{"langcode":"fi","text":"2018-2019, 4. periodi"},{"langcode":"sv","text":"2018-2019, 4. perioden"},{"langcode":"en","text":"2018-2019, 4. period"}]},{"id":68258205,"start_date":"2019-05-05T21:00:00.000Z","end_date":"2019-08-31T21:00:00.000Z","abbreviation":[{"langcode":"fi","text":"Kesä"},{"langcode":"sv","text":"Sommar"},{"langcode":"en","text":"Summer"}],"name":[{"langcode":"fi","text":"2018-2019, Kesä"},{"langcode":"sv","text":"2018-2019, Sommaren"},{"langcode":"en","text":"2018-2019, Summer"}]},{"id":68258233,"start_date":"2019-09-03T21:00:00.000Z","end_date":"2019-10-21T21:00:00.000Z","abbreviation":[{"langcode":"fi","text":"1"},{"langcode":"sv","text":"1"},{"langcode":"en","text":"1"}],"name":[{"langcode":"fi","text":"2019-2020, 1. periodi"},{"langcode":"sv","text":"2019-2020, 1. perioden"},{"langcode":"en","text":"2019-2020, 1. period"}]},{"id":68258234,"start_date":"2019-10-30T22:00:00.000Z","end_date":"2019-12-17T22:00:00.000Z","abbreviation":[{"langcode":"fi","text":"2"},{"langcode":"sv","text":"2"},{"langcode":"en","text":"2"}],"name":[{"langcode":"fi","text":"2019-2020, 2. periodi"},{"langcode":"sv","text":"2019-2020, 2. perioden"},{"langcode":"en","text":"2019-2020, 2. period"}]},{"id":68258235,"start_date":"2020-01-15T22:00:00.000Z","end_date":"2020-03-04T22:00:00.000Z","abbreviation":[{"langcode":"fi","text":"3"},{"langcode":"sv","text":"3"},{"langcode":"en","text":"3"}],"name":[{"langcode":"fi","text":"2019-2020, 3. periodi"},{"langcode":"sv","text":"2019-2020, 3. perioden"},{"langcode":"en","text":"2019-2020, 3. period"}]},{"id":68258236,"start_date":"2020-03-12T22:00:00.000Z","end_date":"2020-05-06T21:00:00.000Z","abbreviation":[{"langcode":"fi","text":"4"},{"langcode":"sv","text":"4"},{"langcode":"en","text":"4"}],"name":[{"langcode":"fi","text":"2019-2020, 4. periodi"},{"langcode":"sv","text":"2019-2020, 4. perioden"},{"langcode":"en","text":"2019-2020, 4. period"}]},{"id":68258238,"start_date":"2020-05-07T21:00:00.000Z","end_date":"2020-09-02T21:00:00.000Z","abbreviation":[{"langcode":"fi","text":"Kesä"},{"langcode":"sv","text":"Sommar"},{"langcode":"en","text":"Summer"}],"name":[{"langcode":"fi","text":"2019-2020, Kesä"},{"langcode":"sv","text":"2019-2020, Sommaren"},{"langcode":"en","text":"2019-2020, Summer"}]},{"id":115562350,"start_date":"2020-08-30T21:00:00.000Z","end_date":"2020-10-17T21:00:00.000Z","abbreviation":[{"langcode":"fi","text":"1"},{"langcode":"sv","text":"1"},{"langcode":"en","text":"1"}],"name":[{"langcode":"fi","text":"2020-2021, 1. periodi"},{"langcode":"sv","text":"2020-2021, 1. perioden"},{"langcode":"en","text":"2020-2021, 1. period"}]},{"id":115563026,"start_date":"2020-10-25T22:00:00.000Z","end_date":"2020-12-12T22:00:00.000Z","abbreviation":[{"langcode":"fi","text":"2"},{"langcode":"sv","text":"2"},{"langcode":"en","text":"2"}],"name":[{"langcode":"fi","text":"2020-2021, 2. periodi"},{"langcode":"sv","text":"2020-2021, 2. perioden"},{"langcode":"en","text":"2020-2021, 2. period"}]},{"id":115563362,"start_date":"2021-01-17T22:00:00.000Z","end_date":"2021-03-06T22:00:00.000Z","abbreviation":[{"langcode":"fi","text":"3"},{"langcode":"sv","text":"3"},{"langcode":"en","text":"3"}],"name":[{"langcode":"fi","text":"2020-2021, 3. periodi"},{"langcode":"sv","text":"2020-2021, 3. perioden"},{"langcode":"en","text":"2020-2021, 3. period"}]},{"id":115563483,"start_date":"2021-03-14T22:00:00.000Z","end_date":"2021-05-08T21:00:00.000Z","abbreviation":[{"langcode":"fi","text":"4"},{"langcode":"sv","text":"4"},{"langcode":"en","text":"4"}],"name":[{"langcode":"fi","text":"2020-2021, 4. periodi"},{"langcode":"sv","text":"2020-2021, 4. perioden"},{"langcode":"en","text":"2020-2021, 4. period"}]},{"id":115563697,"start_date":"2021-05-09T21:00:00.000Z","end_date":"2021-09-04T21:00:00.000Z","abbreviation":[{"langcode":"fi","text":"Kesä"},{"langcode":"sv","text":"Sommar"},{"langcode":"en","text":"Summer"}],"name":[{"langcode":"fi","text":"2020-2021, Kesä"},{"langcode":"sv","text":"2020-2021, Sommaren"},{"langcode":"en","text":"2020-2021, Summer"}]},{"id":115752694,"start_date":"2021-09-05T21:00:00.000Z","end_date":"2021-10-23T21:00:00.000Z","abbreviation":[{"langcode":"fi","text":"1"},{"langcode":"sv","text":"1"},{"langcode":"en","text":"1"}],"name":[{"langcode":"fi","text":"2021-2022, 1. periodi"},{"langcode":"sv","text":"2021-2022, 1. perioden"},{"langcode":"en","text":"2021-2022, 1. period"}]},{"id":115752794,"start_date":"2021-10-31T22:00:00.000Z","end_date":"2021-12-18T22:00:00.000Z","abbreviation":[{"langcode":"fi","text":"2"},{"langcode":"sv","text":"2"},{"langcode":"en","text":"2"}],"name":[{"langcode":"fi","text":"2021-2022, 2. periodi"},{"langcode":"sv","text":"2021-2022, 2. perioden"},{"langcode":"en","text":"2021-2022, 2. period"}]},{"id":115752806,"start_date":"2022-01-16T22:00:00.000Z","end_date":"2022-03-05T22:00:00.000Z","abbreviation":[{"langcode":"fi","text":"3"},{"langcode":"sv","text":"3"},{"langcode":"en","text":"3"}],"name":[{"langcode":"fi","text":"2021-2022, 3. periodi"},{"langcode":"sv","text":"2021-2022, 3. perioden"},{"langcode":"en","text":"2021-2022, 3. period"}]},{"id":115752835,"start_date":"2022-03-13T22:00:00.000Z","end_date":"2022-05-07T21:00:00.000Z","abbreviation":[{"langcode":"fi","text":"4"},{"langcode":"sv","text":"4"},{"langcode":"en","text":"4"}],"name":[{"langcode":"fi","text":"2021-2022, 4. periodi"},{"langcode":"sv","text":"2021-2022, 4. perioden"},{"langcode":"en","text":"2021-2022, 4. period"}]},{"id":115752899,"start_date":"2022-09-04T21:00:00.000Z","end_date":"2022-10-22T21:00:00.000Z","abbreviation":[{"langcode":"fi","text":"1"},{"langcode":"sv","text":"1"},{"langcode":"en","text":"1"}],"name":[{"langcode":"fi","text":"2022-2023, 1. periodi"},{"langcode":"sv","text":"2022-2023, 1. perioden"},{"langcode":"en","text":"2022-2023, 1. period"}]},{"id":115752928,"start_date":"2022-10-30T22:00:00.000Z","end_date":"2022-12-17T22:00:00.000Z","abbreviation":[{"langcode":"fi","text":"2"},{"langcode":"sv","text":"2"},{"langcode":"en","text":"2"}],"name":[{"langcode":"fi","text":"2022-2023, 2. periodi"},{"langcode":"sv","text":"2022-2023, 2. perioden"},{"langcode":"en","text":"2022-2023, 2. period"}]},{"id":115756716,"start_date":"2023-01-15T22:00:00.000Z","end_date":"2023-03-04T22:00:00.000Z","abbreviation":[{"langcode":"fi","text":"3"},{"langcode":"sv","text":"3"},{"langcode":"en","text":"3"}],"name":[{"langcode":"fi","text":"2022-2023, 3. periodi"},{"langcode":"sv","text":"2022-2023, 3. perioden"},{"langcode":"en","text":"2022-2023, 3. period"}]},{"id":115756829,"start_date":"2023-03-12T22:00:00.000Z","end_date":"2023-05-06T21:00:00.000Z","abbreviation":[{"langcode":"fi","text":"4"},{"langcode":"sv","text":"4"},{"langcode":"en","text":"4"}],"name":[{"langcode":"fi","text":"2022-2023, 4. periodi"},{"langcode":"sv","text":"2022-2023, 4. perioden"},{"langcode":"en","text":"2022-2023, 4. period"}]},{"id":115756875,"start_date":"2022-05-08T21:00:00.000Z","end_date":"2022-09-03T21:00:00.000Z","abbreviation":[{"langcode":"fi","text":"Kesä"},{"langcode":"sv","text":"Sommar"},{"langcode":"en","text":"Summer"}],"name":[{"langcode":"fi","text":"2021-2022, Kesä"},{"langcode":"sv","text":"2021-2022, Sommaren"},{"langcode":"en","text":"2021-2022, Summer"}]},{"id":115756911,"start_date":"2023-05-07T21:00:00.000Z","end_date":"2023-09-02T21:00:00.000Z","abbreviation":[{"langcode":"fi","text":"Kesä"},{"langcode":"sv","text":"Sommar"},{"langcode":"en","text":"Summer"}],"name":[{"langcode":"fi","text":"2022-2023, Kesä"},{"langcode":"sv","text":"2022-2023, Sommaren"},{"langcode":"en","text":"2022-2023, Summer"}]}]}